AndroidShentouCeshiXuexiShouce/README.md
AndroidShentouCeshiXuexiShouce/__init__.py
AndroidShentouCeshiXuexiShouce/__main__.py
AndroidShentouCeshiXuexiShouce/file.epub
AndroidShentouCeshiXuexiShouce/index.html
AndroidShentouCeshiXuexiShouce/css/__init__.py
AndroidShentouCeshiXuexiShouce/css/annotations.css
AndroidShentouCeshiXuexiShouce/css/main.css
AndroidShentouCeshiXuexiShouce/css/normalize.css
AndroidShentouCeshiXuexiShouce/css/popup.css
AndroidShentouCeshiXuexiShouce/font/__init__.py
AndroidShentouCeshiXuexiShouce/font/fontello.eot
AndroidShentouCeshiXuexiShouce/font/fontello.svg
AndroidShentouCeshiXuexiShouce/font/fontello.ttf
AndroidShentouCeshiXuexiShouce/font/fontello.woff
AndroidShentouCeshiXuexiShouce/img/__init__.py
AndroidShentouCeshiXuexiShouce/img/annotator-glyph-sprite.png
AndroidShentouCeshiXuexiShouce/img/annotator-icon-sprite.png
AndroidShentouCeshiXuexiShouce/img/apple-touch-icon.png
AndroidShentouCeshiXuexiShouce/img/cancelfullscreen.png
AndroidShentouCeshiXuexiShouce/img/close.png
AndroidShentouCeshiXuexiShouce/img/fullscreen.png
AndroidShentouCeshiXuexiShouce/img/loader.gif
AndroidShentouCeshiXuexiShouce/img/menu-icon.png
AndroidShentouCeshiXuexiShouce/img/save.png
AndroidShentouCeshiXuexiShouce/img/saved.png
AndroidShentouCeshiXuexiShouce/img/settings-s.png
AndroidShentouCeshiXuexiShouce/img/settings.png
AndroidShentouCeshiXuexiShouce/img/star.png
AndroidShentouCeshiXuexiShouce/js/__init__.py
AndroidShentouCeshiXuexiShouce/js/epub.js
AndroidShentouCeshiXuexiShouce/js/epub.min.js
AndroidShentouCeshiXuexiShouce/js/epub.min.map
AndroidShentouCeshiXuexiShouce/js/hooks.min.js
AndroidShentouCeshiXuexiShouce/js/hooks.min.map
AndroidShentouCeshiXuexiShouce/js/reader.js
AndroidShentouCeshiXuexiShouce/js/reader.js.map
AndroidShentouCeshiXuexiShouce/js/reader.min.js
AndroidShentouCeshiXuexiShouce/js/reader.min.map
AndroidShentouCeshiXuexiShouce/js/hooks/__init__.py
AndroidShentouCeshiXuexiShouce/js/hooks/extensions/__init__.py
android_shentou_ceshi_xuexi_shouce-2024.2.29.0.dist-info/METADATA
android_shentou_ceshi_xuexi_shouce-2024.2.29.0.dist-info/WHEEL
android_shentou_ceshi_xuexi_shouce-2024.2.29.0.dist-info/entry_points.txt
android_shentou_ceshi_xuexi_shouce-2024.2.29.0.dist-info/top_level.txt
android_shentou_ceshi_xuexi_shouce-2024.2.29.0.dist-info/RECORD
